{"cameraMode":{"drawMode":0,"name":"Shaded","section":"Shading Mode"},"sceneLighting":true,"audioPlay":false,"sceneViewState":{"showFog":true,"showMaterialUpdate":false,"showSkybox":true,"showFlares":true,"showImageEffects":true,"showParticleSystems":true},"in2DMode":false,"pivot":{"x":1.5744307041168213,"y":1.0104132890701295,"z":1.2704472541809083},"rotation":{"x":0.05780782923102379,"y":-0.2835187017917633,"z":0.017123665660619737,"w":0.9570696353912354},"size":6.360503196716309,"orthographic":false}